{
  "Caprese Pizza": {
    "duration_ms": 20527,
    "ingredients": 25,
    "steps": 17,
    "success": true,
    "title": "Heirloom Tomato Caprese Pizza"
  },
  "Eitan TikTok Recipe 1": {
    "error": "Video extraction requires download step - skipping",
    "success": false
  },
  "Eitan TikTok Recipe 2": {
    "error": "Video extraction requires download step - skipping",
    "success": false
  },
  "Peanut Butter Swirl Brownies": {
    "duration_ms": 11006,
    "ingredients": 14,
    "steps": 9,
    "success": true,
    "title": "Peanut Butter Swirl Brownies"
  },
  "Sesame Schnitzel": {
    "duration_ms": 10128,
    "ingredients": 29,
    "steps": 0,
    "success": true,
    "title": "Sesame Schnitzel Topped With Loaded Salad"
  }
}